cuda_functions
