Metadata-Version: 1.1
Name: cuda_functions
Version: 0.9.4.1
Summary: cuda_functions module
Home-page: https://github.com/abelcarreras/cuda_functions
Author: Abel Carreras
Author-email: abelcarreras83@gmail.com
License: MIT License
Platform: UNKNOWN
Requires: numpy
